{
  "classname": null,
  "name": null,
  "animation": {
    "classname": null,
    "name": "AnimationManager",
    "actionlist": []
  },
  "dataScale": 1,
  "designHeight": 720,
  "designWidth": 1280,
  "textures": [
    "majiangtu/majiang_pai02.plist",
    "majiangtu/majiang_pai_wenzi.plist"
  ],
  "texturesPng": [
    "touming.png",
    "majiangtu/majiang_pai02.plist",
    "majiangtu/majiang_pai_wenzi.plist"
  ],
  "version": "1.6.0.0",
  "widgetTree": {
    "classname": "Panel",
    "name": null,
    "children": [
      {
        "classname": "ImageView",
        "name": null,
        "children": [
          {
            "classname": "ImageView",
            "name": null,
            "children": [
              {
                "classname": "ImageView",
                "name": null,
                "children": [],
                "options": {
                  "__type": "ImageViewSurrogate:#EditorCommon.JsonModel.Component.GUI",
                  "classname": "ImageView",
                  "name": "sv",
                  "ZOrder": 0,
                  "actiontag": 11007286,
                  "anchorPointX": 0.5,
                  "anchorPointY": 0.5,
                  "classType": "CocoStudio.EngineAdapterWrap.CSImageView",
                  "colorB": 255,
                  "colorG": 255,
                  "colorR": 255,
                  "customProperty": "",
                  "flipX": true,
                  "flipY": false,
                  "height": 114,
                  "ignoreSize": true,
                  "layoutParameter": null,
                  "opacity": 255,
                  "positionPercentX": 0.08108108,
                  "positionPercentY": 0.218181819,
                  "positionType": 0,
                  "rotation": 90,
                  "scaleX": 0.4,
                  "scaleY": 0.6,
                  "sizePercentX": 1.10810816,
                  "sizePercentY": 2.0727272,
                  "sizeType": 0,
                  "tag": 185235,
                  "touchAble": false,
                  "useMergedTexture": false,
                  "visible": true,
                  "width": 82,
                  "x": 6,
                  "y": 12,
                  "capInsetsHeight": 1,
                  "capInsetsWidth": 1,
                  "capInsetsX": 0,
                  "capInsetsY": 0,
                  "fileName": null,
                  "fileNameData": {
                    "path": "7wan.png",
                    "plistFile": "majiangtu/majiang_pai_wenzi.plist",
                    "resourceType": 1
                  },
                  "scale9Enable": false,
                  "scale9Height": 114,
                  "scale9Width": 82
                }
              }
            ],
            "options": {
              "__type": "ImageViewSurrogate:#EditorCommon.JsonModel.Component.GUI",
              "classname": "ImageView",
              "name": "c1",
              "ZOrder": 0,
              "actiontag": 15877477,
              "anchorPointX": 0.5,
              "anchorPointY": 0.5,
              "classType": "CocoStudio.EngineAdapterWrap.CSImageView",
              "colorB": 255,
              "colorG": 255,
              "colorR": 255,
              "customProperty": "",
              "flipX": true,
              "flipY": false,
              "height": 55,
              "ignoreSize": true,
              "layoutParameter": null,
              "opacity": 255,
              "positionPercentX": -0.326666653,
              "positionPercentY": 0.48,
              "positionType": 0,
              "rotation": 0,
              "scaleX": 1,
              "scaleY": 1,
              "sizePercentX": 0.49333334,
              "sizePercentY": 0.11,
              "sizeType": 0,
              "tag": 185234,
              "touchAble": false,
              "useMergedTexture": false,
              "visible": true,
              "width": 74,
              "x": -49,
              "y": 240,
              "capInsetsHeight": 1,
              "capInsetsWidth": 1,
              "capInsetsX": 0,
              "capInsetsY": 0,
              "fileName": null,
              "fileNameData": {
                "path": "majiang_pai_sj_hp_00.png",
                "plistFile": "majiangtu/majiang_pai02.plist",
                "resourceType": 1
              },
              "scale9Enable": false,
              "scale9Height": 55,
              "scale9Width": 74
            }
          },
          {
            "classname": "ImageView",
            "name": null,
            "children": [
              {
                "classname": "ImageView",
                "name": null,
                "children": [],
                "options": {
                  "__type": "ImageViewSurrogate:#EditorCommon.JsonModel.Component.GUI",
                  "classname": "ImageView",
                  "name": "sv",
                  "ZOrder": 0,
                  "actiontag": 19175012,
                  "anchorPointX": 0.5,
                  "anchorPointY": 0.5,
                  "classType": "CocoStudio.EngineAdapterWrap.CSImageView",
                  "colorB": 255,
                  "colorG": 255,
                  "colorR": 255,
                  "customProperty": "",
                  "flipX": true,
                  "flipY": false,
                  "height": 114,
                  "ignoreSize": true,
                  "layoutParameter": null,
                  "opacity": 255,
                  "positionPercentX": 0.08108108,
                  "positionPercentY": 0.218181819,
                  "positionType": 0,
                  "rotation": 90,
                  "scaleX": 0.4,
                  "scaleY": 0.6,
                  "sizePercentX": 1.10810816,
                  "sizePercentY": 2.0727272,
                  "sizeType": 0,
                  "tag": 185237,
                  "touchAble": false,
                  "useMergedTexture": false,
                  "visible": true,
                  "width": 82,
                  "x": 6,
                  "y": 12,
                  "capInsetsHeight": 1,
                  "capInsetsWidth": 1,
                  "capInsetsX": 0,
                  "capInsetsY": 0,
                  "fileName": null,
                  "fileNameData": {
                    "path": "7wan.png",
                    "plistFile": "majiangtu/majiang_pai_wenzi.plist",
                    "resourceType": 1
                  },
                  "scale9Enable": false,
                  "scale9Height": 114,
                  "scale9Width": 82
                }
              }
            ],
            "options": {
              "__type": "ImageViewSurrogate:#EditorCommon.JsonModel.Component.GUI",
              "classname": "ImageView",
              "name": "c2",
              "ZOrder": 0,
              "actiontag": 31956718,
              "anchorPointX": 0.5,
              "anchorPointY": 0.5,
              "classType": "CocoStudio.EngineAdapterWrap.CSImageView",
              "colorB": 255,
              "colorG": 255,
              "colorR": 255,
              "customProperty": "",
              "flipX": true,
              "flipY": false,
              "height": 55,
              "ignoreSize": true,
              "layoutParameter": null,
              "opacity": 255,
              "positionPercentX": -0.24666667,
              "positionPercentY": 0.366,
              "positionType": 0,
              "rotation": 0,
              "scaleX": 1.01,
              "scaleY": 1.01,
              "sizePercentX": 0.49333334,
              "sizePercentY": 0.11,
              "sizeType": 0,
              "tag": 185236,
              "touchAble": false,
              "useMergedTexture": false,
              "visible": true,
              "width": 74,
              "x": -37,
              "y": 183,
              "capInsetsHeight": 1,
              "capInsetsWidth": 1,
              "capInsetsX": 0,
              "capInsetsY": 0,
              "fileName": null,
              "fileNameData": {
                "path": "majiang_pai_sj_hp_00.png",
                "plistFile": "majiangtu/majiang_pai02.plist",
                "resourceType": 1
              },
              "scale9Enable": false,
              "scale9Height": 55,
              "scale9Width": 74
            }
          },
          {
            "classname": "ImageView",
            "name": null,
            "children": [
              {
                "classname": "ImageView",
                "name": null,
                "children": [],
                "options": {
                  "__type": "ImageViewSurrogate:#EditorCommon.JsonModel.Component.GUI",
                  "classname": "ImageView",
                  "name": "sv",
                  "ZOrder": 0,
                  "actiontag": 9672150,
                  "anchorPointX": 0.5,
                  "anchorPointY": 0.5,
                  "classType": "CocoStudio.EngineAdapterWrap.CSImageView",
                  "colorB": 255,
                  "colorG": 255,
                  "colorR": 255,
                  "customProperty": "",
                  "flipX": true,
                  "flipY": false,
                  "height": 114,
                  "ignoreSize": true,
                  "layoutParameter": null,
                  "opacity": 255,
                  "positionPercentX": 0.08108108,
                  "positionPercentY": 0.218181819,
                  "positionType": 0,
                  "rotation": 90,
                  "scaleX": 0.4,
                  "scaleY": 0.6,
                  "sizePercentX": 1.10810816,
                  "sizePercentY": 2.0727272,
                  "sizeType": 0,
                  "tag": 185239,
                  "touchAble": false,
                  "useMergedTexture": false,
                  "visible": true,
                  "width": 82,
                  "x": 6,
                  "y": 12,
                  "capInsetsHeight": 1,
                  "capInsetsWidth": 1,
                  "capInsetsX": 0,
                  "capInsetsY": 0,
                  "fileName": null,
                  "fileNameData": {
                    "path": "7wan.png",
                    "plistFile": "majiangtu/majiang_pai_wenzi.plist",
                    "resourceType": 1
                  },
                  "scale9Enable": false,
                  "scale9Height": 114,
                  "scale9Width": 82
                }
              }
            ],
            "options": {
              "__type": "ImageViewSurrogate:#EditorCommon.JsonModel.Component.GUI",
              "classname": "ImageView",
              "name": "c3",
              "ZOrder": 0,
              "actiontag": 38357385,
              "anchorPointX": 0.5,
              "anchorPointY": 0.5,
              "classType": "CocoStudio.EngineAdapterWrap.CSImageView",
              "colorB": 255,
              "colorG": 255,
              "colorR": 255,
              "customProperty": "",
              "flipX": true,
              "flipY": false,
              "height": 55,
              "ignoreSize": true,
              "layoutParameter": null,
              "opacity": 255,
              "positionPercentX": -0.2,
              "positionPercentY": 0.294,
              "positionType": 0,
              "rotation": 0,
              "scaleX": 1.02,
              "scaleY": 1.02,
              "sizePercentX": 0.49333334,
              "sizePercentY": 0.11,
              "sizeType": 0,
              "tag": 185238,
              "touchAble": false,
              "useMergedTexture": false,
              "visible": true,
              "width": 74,
              "x": -30,
              "y": 147,
              "capInsetsHeight": 1,
              "capInsetsWidth": 1,
              "capInsetsX": 0,
              "capInsetsY": 0,
              "fileName": null,
              "fileNameData": {
                "path": "majiang_pai_sj_hp_00.png",
                "plistFile": "majiangtu/majiang_pai02.plist",
                "resourceType": 1
              },
              "scale9Enable": false,
              "scale9Height": 55,
              "scale9Width": 74
            }
          },
          {
            "classname": "ImageView",
            "name": null,
            "children": [
              {
                "classname": "ImageView",
                "name": null,
                "children": [],
                "options": {
                  "__type": "ImageViewSurrogate:#EditorCommon.JsonModel.Component.GUI",
                  "classname": "ImageView",
                  "name": "sv",
                  "ZOrder": 0,
                  "actiontag": 45246709,
                  "anchorPointX": 0.5,
                  "anchorPointY": 0.5,
                  "classType": "CocoStudio.EngineAdapterWrap.CSImageView",
                  "colorB": 255,
                  "colorG": 255,
                  "colorR": 255,
                  "customProperty": "",
                  "flipX": true,
                  "flipY": false,
                  "height": 114,
                  "ignoreSize": true,
                  "layoutParameter": null,
                  "opacity": 255,
                  "positionPercentX": 0.08108108,
                  "positionPercentY": 0.218181819,
                  "positionType": 0,
                  "rotation": 90,
                  "scaleX": 0.4,
                  "scaleY": 0.6,
                  "sizePercentX": 1.10810816,
                  "sizePercentY": 2.0727272,
                  "sizeType": 0,
                  "tag": 185241,
                  "touchAble": false,
                  "useMergedTexture": false,
                  "visible": true,
                  "width": 82,
                  "x": 6,
                  "y": 12,
                  "capInsetsHeight": 1,
                  "capInsetsWidth": 1,
                  "capInsetsX": 0,
                  "capInsetsY": 0,
                  "fileName": null,
                  "fileNameData": {
                    "path": "7wan.png",
                    "plistFile": "majiangtu/majiang_pai_wenzi.plist",
                    "resourceType": 1
                  },
                  "scale9Enable": false,
                  "scale9Height": 114,
                  "scale9Width": 82
                }
              }
            ],
            "options": {
              "__type": "ImageViewSurrogate:#EditorCommon.JsonModel.Component.GUI",
              "classname": "ImageView",
              "name": "c4",
              "ZOrder": 0,
              "actiontag": 19940493,
              "anchorPointX": 0.5,
              "anchorPointY": 0.5,
              "classType": "CocoStudio.EngineAdapterWrap.CSImageView",
              "colorB": 255,
              "colorG": 255,
              "colorR": 255,
              "customProperty": "",
              "flipX": true,
              "flipY": false,
              "height": 55,
              "ignoreSize": true,
              "layoutParameter": null,
              "opacity": 255,
              "positionPercentX": -0.146666661,
              "positionPercentY": 0.22,
              "positionType": 0,
              "rotation": 0,
              "scaleX": 1.03,
              "scaleY": 1.03,
              "sizePercentX": 0.49333334,
              "sizePercentY": 0.11,
              "sizeType": 0,
              "tag": 185240,
              "touchAble": false,
              "useMergedTexture": false,
              "visible": true,
              "width": 74,
              "x": -22,
              "y": 110,
              "capInsetsHeight": 1,
              "capInsetsWidth": 1,
              "capInsetsX": 0,
              "capInsetsY": 0,
              "fileName": null,
              "fileNameData": {
                "path": "majiang_pai_sj_hp_00.png",
                "plistFile": "majiangtu/majiang_pai02.plist",
                "resourceType": 1
              },
              "scale9Enable": false,
              "scale9Height": 55,
              "scale9Width": 74
            }
          },
          {
            "classname": "ImageView",
            "name": null,
            "children": [
              {
                "classname": "ImageView",
                "name": null,
                "children": [],
                "options": {
                  "__type": "ImageViewSurrogate:#EditorCommon.JsonModel.Component.GUI",
                  "classname": "ImageView",
                  "name": "sv",
                  "ZOrder": 0,
                  "actiontag": 41104808,
                  "anchorPointX": 0.5,
                  "anchorPointY": 0.5,
                  "classType": "CocoStudio.EngineAdapterWrap.CSImageView",
                  "colorB": 255,
                  "colorG": 255,
                  "colorR": 255,
                  "customProperty": "",
                  "flipX": true,
                  "flipY": false,
                  "height": 114,
                  "ignoreSize": true,
                  "layoutParameter": null,
                  "opacity": 255,
                  "positionPercentX": 0.08108108,
                  "positionPercentY": 0.218181819,
                  "positionType": 0,
                  "rotation": 90,
                  "scaleX": 0.4,
                  "scaleY": 0.6,
                  "sizePercentX": 1.10810816,
                  "sizePercentY": 2.0727272,
                  "sizeType": 0,
                  "tag": 185243,
                  "touchAble": false,
                  "useMergedTexture": false,
                  "visible": true,
                  "width": 82,
                  "x": 6,
                  "y": 12,
                  "capInsetsHeight": 1,
                  "capInsetsWidth": 1,
                  "capInsetsX": 0,
                  "capInsetsY": 0,
                  "fileName": null,
                  "fileNameData": {
                    "path": "7wan.png",
                    "plistFile": "majiangtu/majiang_pai_wenzi.plist",
                    "resourceType": 1
                  },
                  "scale9Enable": false,
                  "scale9Height": 114,
                  "scale9Width": 82
                }
              }
            ],
            "options": {
              "__type": "ImageViewSurrogate:#EditorCommon.JsonModel.Component.GUI",
              "classname": "ImageView",
              "name": "c5",
              "ZOrder": 0,
              "actiontag": 4567200,
              "anchorPointX": 0.5,
              "anchorPointY": 0.5,
              "classType": "CocoStudio.EngineAdapterWrap.CSImageView",
              "colorB": 255,
              "colorG": 255,
              "colorR": 255,
              "customProperty": "",
              "flipX": true,
              "flipY": false,
              "height": 55,
              "ignoreSize": true,
              "layoutParameter": null,
              "opacity": 255,
              "positionPercentX": -0.086666666,
              "positionPercentY": 0.146,
              "positionType": 0,
              "rotation": 0,
              "scaleX": 1.04,
              "scaleY": 1.04,
              "sizePercentX": 0.49333334,
              "sizePercentY": 0.11,
              "sizeType": 0,
              "tag": 185242,
              "touchAble": false,
              "useMergedTexture": false,
              "visible": true,
              "width": 74,
              "x": -13,
              "y": 73,
              "capInsetsHeight": 1,
              "capInsetsWidth": 1,
              "capInsetsX": 0,
              "capInsetsY": 0,
              "fileName": null,
              "fileNameData": {
                "path": "majiang_pai_sj_hp_00.png",
                "plistFile": "majiangtu/majiang_pai02.plist",
                "resourceType": 1
              },
              "scale9Enable": false,
              "scale9Height": 55,
              "scale9Width": 74
            }
          },
          {
            "classname": "ImageView",
            "name": null,
            "children": [
              {
                "classname": "ImageView",
                "name": null,
                "children": [],
                "options": {
                  "__type": "ImageViewSurrogate:#EditorCommon.JsonModel.Component.GUI",
                  "classname": "ImageView",
                  "name": "sv",
                  "ZOrder": 0,
                  "actiontag": 22544354,
                  "anchorPointX": 0.5,
                  "anchorPointY": 0.5,
                  "classType": "CocoStudio.EngineAdapterWrap.CSImageView",
                  "colorB": 255,
                  "colorG": 255,
                  "colorR": 255,
                  "customProperty": "",
                  "flipX": true,
                  "flipY": false,
                  "height": 114,
                  "ignoreSize": true,
                  "layoutParameter": null,
                  "opacity": 255,
                  "positionPercentX": 0.08108108,
                  "positionPercentY": 0.218181819,
                  "positionType": 0,
                  "rotation": 90,
                  "scaleX": 0.4,
                  "scaleY": 0.6,
                  "sizePercentX": 1.10810816,
                  "sizePercentY": 2.0727272,
                  "sizeType": 0,
                  "tag": 185245,
                  "touchAble": false,
                  "useMergedTexture": false,
                  "visible": true,
                  "width": 82,
                  "x": 6,
                  "y": 12,
                  "capInsetsHeight": 1,
                  "capInsetsWidth": 1,
                  "capInsetsX": 0,
                  "capInsetsY": 0,
                  "fileName": null,
                  "fileNameData": {
                    "path": "7wan.png",
                    "plistFile": "majiangtu/majiang_pai_wenzi.plist",
                    "resourceType": 1
                  },
                  "scale9Enable": false,
                  "scale9Height": 114,
                  "scale9Width": 82
                }
              }
            ],
            "options": {
              "__type": "ImageViewSurrogate:#EditorCommon.JsonModel.Component.GUI",
              "classname": "ImageView",
              "name": "c6",
              "ZOrder": 0,
              "actiontag": 24874549,
              "anchorPointX": 0.5,
              "anchorPointY": 0.5,
              "classType": "CocoStudio.EngineAdapterWrap.CSImageView",
              "colorB": 255,
              "colorG": 255,
              "colorR": 255,
              "customProperty": "",
              "flipX": true,
              "flipY": false,
              "height": 55,
              "ignoreSize": true,
              "layoutParameter": null,
              "opacity": 255,
              "positionPercentX": -0.0333333351,
              "positionPercentY": 0.07,
              "positionType": 0,
              "rotation": 0,
              "scaleX": 1.05,
              "scaleY": 1.05,
              "sizePercentX": 0.49333334,
              "sizePercentY": 0.11,
              "sizeType": 0,
              "tag": 185244,
              "touchAble": false,
              "useMergedTexture": false,
              "visible": true,
              "width": 74,
              "x": -5,
              "y": 35,
              "capInsetsHeight": 1,
              "capInsetsWidth": 1,
              "capInsetsX": 0,
              "capInsetsY": 0,
              "fileName": null,
              "fileNameData": {
                "path": "majiang_pai_sj_hp_00.png",
                "plistFile": "majiangtu/majiang_pai02.plist",
                "resourceType": 1
              },
              "scale9Enable": false,
              "scale9Height": 55,
              "scale9Width": 74
            }
          },
          {
            "classname": "ImageView",
            "name": null,
            "children": [
              {
                "classname": "ImageView",
                "name": null,
                "children": [],
                "options": {
                  "__type": "ImageViewSurrogate:#EditorCommon.JsonModel.Component.GUI",
                  "classname": "ImageView",
                  "name": "sv",
                  "ZOrder": 0,
                  "actiontag": 14153363,
                  "anchorPointX": 0.5,
                  "anchorPointY": 0.5,
                  "classType": "CocoStudio.EngineAdapterWrap.CSImageView",
                  "colorB": 255,
                  "colorG": 255,
                  "colorR": 255,
                  "customProperty": "",
                  "flipX": true,
                  "flipY": false,
                  "height": 114,
                  "ignoreSize": true,
                  "layoutParameter": null,
                  "opacity": 255,
                  "positionPercentX": 0.08108108,
                  "positionPercentY": 0.218181819,
                  "positionType": 0,
                  "rotation": 90,
                  "scaleX": 0.4,
                  "scaleY": 0.6,
                  "sizePercentX": 1.10810816,
                  "sizePercentY": 2.0727272,
                  "sizeType": 0,
                  "tag": 185247,
                  "touchAble": false,
                  "useMergedTexture": false,
                  "visible": true,
                  "width": 82,
                  "x": 6,
                  "y": 12,
                  "capInsetsHeight": 1,
                  "capInsetsWidth": 1,
                  "capInsetsX": 0,
                  "capInsetsY": 0,
                  "fileName": null,
                  "fileNameData": {
                    "path": "7wan.png",
                    "plistFile": "majiangtu/majiang_pai_wenzi.plist",
                    "resourceType": 1
                  },
                  "scale9Enable": false,
                  "scale9Height": 114,
                  "scale9Width": 82
                }
              }
            ],
            "options": {
              "__type": "ImageViewSurrogate:#EditorCommon.JsonModel.Component.GUI",
              "classname": "ImageView",
              "name": "c7",
              "ZOrder": 0,
              "actiontag": 1572595,
              "anchorPointX": 0.5,
              "anchorPointY": 0.5,
              "classType": "CocoStudio.EngineAdapterWrap.CSImageView",
              "colorB": 255,
              "colorG": 255,
              "colorR": 255,
              "customProperty": "",
              "flipX": true,
              "flipY": false,
              "height": 55,
              "ignoreSize": true,
              "layoutParameter": null,
              "opacity": 255,
              "positionPercentX": 0.0133333337,
              "positionPercentY": -0.002,
              "positionType": 0,
              "rotation": 0,
              "scaleX": 1.06,
              "scaleY": 1.06,
              "sizePercentX": 0.49333334,
              "sizePercentY": 0.11,
              "sizeType": 0,
              "tag": 185246,
              "touchAble": false,
              "useMergedTexture": false,
              "visible": true,
              "width": 74,
              "x": 2,
              "y": -1,
              "capInsetsHeight": 1,
              "capInsetsWidth": 1,
              "capInsetsX": 0,
              "capInsetsY": 0,
              "fileName": null,
              "fileNameData": {
                "path": "majiang_pai_sj_hp_00.png",
                "plistFile": "majiangtu/majiang_pai02.plist",
                "resourceType": 1
              },
              "scale9Enable": false,
              "scale9Height": 55,
              "scale9Width": 74
            }
          },
          {
            "classname": "ImageView",
            "name": null,
            "children": [
              {
                "classname": "ImageView",
                "name": null,
                "children": [],
                "options": {
                  "__type": "ImageViewSurrogate:#EditorCommon.JsonModel.Component.GUI",
                  "classname": "ImageView",
                  "name": "sv",
                  "ZOrder": 0,
                  "actiontag": 5571786,
                  "anchorPointX": 0.5,
                  "anchorPointY": 0.5,
                  "classType": "CocoStudio.EngineAdapterWrap.CSImageView",
                  "colorB": 255,
                  "colorG": 255,
                  "colorR": 255,
                  "customProperty": "",
                  "flipX": true,
                  "flipY": false,
                  "height": 114,
                  "ignoreSize": true,
                  "layoutParameter": null,
                  "opacity": 255,
                  "positionPercentX": 0.08108108,
                  "positionPercentY": 0.218181819,
                  "positionType": 0,
                  "rotation": 90,
                  "scaleX": 0.4,
                  "scaleY": 0.6,
                  "sizePercentX": 1.10810816,
                  "sizePercentY": 2.0727272,
                  "sizeType": 0,
                  "tag": 185249,
                  "touchAble": false,
                  "useMergedTexture": false,
                  "visible": true,
                  "width": 82,
                  "x": 6,
                  "y": 12,
                  "capInsetsHeight": 1,
                  "capInsetsWidth": 1,
                  "capInsetsX": 0,
                  "capInsetsY": 0,
                  "fileName": null,
                  "fileNameData": {
                    "path": "7wan.png",
                    "plistFile": "majiangtu/majiang_pai_wenzi.plist",
                    "resourceType": 1
                  },
                  "scale9Enable": false,
                  "scale9Height": 114,
                  "scale9Width": 82
                }
              }
            ],
            "options": {
              "__type": "ImageViewSurrogate:#EditorCommon.JsonModel.Component.GUI",
              "classname": "ImageView",
              "name": "c8",
              "ZOrder": 0,
              "actiontag": 60271410,
              "anchorPointX": 0.5,
              "anchorPointY": 0.5,
              "classType": "CocoStudio.EngineAdapterWrap.CSImageView",
              "colorB": 255,
              "colorG": 255,
              "colorR": 255,
              "customProperty": "",
              "flipX": true,
              "flipY": false,
              "height": 55,
              "ignoreSize": true,
              "layoutParameter": null,
              "opacity": 255,
              "positionPercentX": 0.07333333,
              "positionPercentY": -0.078,
              "positionType": 0,
              "rotation": 0,
              "scaleX": 1.07,
              "scaleY": 1.07,
              "sizePercentX": 0.49333334,
              "sizePercentY": 0.11,
              "sizeType": 0,
              "tag": 185248,
              "touchAble": false,
              "useMergedTexture": false,
              "visible": true,
              "width": 74,
              "x": 11,
              "y": -39,
              "capInsetsHeight": 1,
              "capInsetsWidth": 1,
              "capInsetsX": 0,
              "capInsetsY": 0,
              "fileName": null,
              "fileNameData": {
                "path": "majiang_pai_sj_hp_00.png",
                "plistFile": "majiangtu/majiang_pai02.plist",
                "resourceType": 1
              },
              "scale9Enable": false,
              "scale9Height": 55,
              "scale9Width": 74
            }
          },
          {
            "classname": "ImageView",
            "name": null,
            "children": [
              {
                "classname": "ImageView",
                "name": null,
                "children": [],
                "options": {
                  "__type": "ImageViewSurrogate:#EditorCommon.JsonModel.Component.GUI",
                  "classname": "ImageView",
                  "name": "sv",
                  "ZOrder": 0,
                  "actiontag": 48661484,
                  "anchorPointX": 0.5,
                  "anchorPointY": 0.5,
                  "classType": "CocoStudio.EngineAdapterWrap.CSImageView",
                  "colorB": 255,
                  "colorG": 255,
                  "colorR": 255,
                  "customProperty": "",
                  "flipX": true,
                  "flipY": false,
                  "height": 114,
                  "ignoreSize": true,
                  "layoutParameter": null,
                  "opacity": 255,
                  "positionPercentX": 0.08108108,
                  "positionPercentY": 0.218181819,
                  "positionType": 0,
                  "rotation": 90,
                  "scaleX": 0.4,
                  "scaleY": 0.6,
                  "sizePercentX": 1.10810816,
                  "sizePercentY": 2.0727272,
                  "sizeType": 0,
                  "tag": 185251,
                  "touchAble": false,
                  "useMergedTexture": false,
                  "visible": true,
                  "width": 82,
                  "x": 6,
                  "y": 12,
                  "capInsetsHeight": 1,
                  "capInsetsWidth": 1,
                  "capInsetsX": 0,
                  "capInsetsY": 0,
                  "fileName": null,
                  "fileNameData": {
                    "path": "7wan.png",
                    "plistFile": "majiangtu/majiang_pai_wenzi.plist",
                    "resourceType": 1
                  },
                  "scale9Enable": false,
                  "scale9Height": 114,
                  "scale9Width": 82
                }
              }
            ],
            "options": {
              "__type": "ImageViewSurrogate:#EditorCommon.JsonModel.Component.GUI",
              "classname": "ImageView",
              "name": "c9",
              "ZOrder": 0,
              "actiontag": 50146074,
              "anchorPointX": 0.5,
              "anchorPointY": 0.5,
              "classType": "CocoStudio.EngineAdapterWrap.CSImageView",
              "colorB": 255,
              "colorG": 255,
              "colorR": 255,
              "customProperty": "",
              "flipX": true,
              "flipY": false,
              "height": 55,
              "ignoreSize": true,
              "layoutParameter": null,
              "opacity": 255,
              "positionPercentX": 0.13333334,
              "positionPercentY": -0.158,
              "positionType": 0,
              "rotation": 0,
              "scaleX": 1.08,
              "scaleY": 1.08,
              "sizePercentX": 0.49333334,
              "sizePercentY": 0.11,
              "sizeType": 0,
              "tag": 185250,
              "touchAble": false,
              "useMergedTexture": false,
              "visible": true,
              "width": 74,
              "x": 20,
              "y": -79,
              "capInsetsHeight": 1,
              "capInsetsWidth": 1,
              "capInsetsX": 0,
              "capInsetsY": 0,
              "fileName": null,
              "fileNameData": {
                "path": "majiang_pai_sj_hp_00.png",
                "plistFile": "majiangtu/majiang_pai02.plist",
                "resourceType": 1
              },
              "scale9Enable": false,
              "scale9Height": 55,
              "scale9Width": 74
            }
          },
          {
            "classname": "ImageView",
            "name": null,
            "children": [
              {
                "classname": "ImageView",
                "name": null,
                "children": [],
                "options": {
                  "__type": "ImageViewSurrogate:#EditorCommon.JsonModel.Component.GUI",
                  "classname": "ImageView",
                  "name": "sv",
                  "ZOrder": 0,
                  "actiontag": 49266147,
                  "anchorPointX": 0.5,
                  "anchorPointY": 0.5,
                  "classType": "CocoStudio.EngineAdapterWrap.CSImageView",
                  "colorB": 255,
                  "colorG": 255,
                  "colorR": 255,
                  "customProperty": "",
                  "flipX": true,
                  "flipY": false,
                  "height": 114,
                  "ignoreSize": true,
                  "layoutParameter": null,
                  "opacity": 255,
                  "positionPercentX": 0.08108108,
                  "positionPercentY": 0.218181819,
                  "positionType": 0,
                  "rotation": 90,
                  "scaleX": 0.4,
                  "scaleY": 0.6,
                  "sizePercentX": 1.10810816,
                  "sizePercentY": 2.0727272,
                  "sizeType": 0,
                  "tag": 185253,
                  "touchAble": false,
                  "useMergedTexture": false,
                  "visible": true,
                  "width": 82,
                  "x": 6,
                  "y": 12,
                  "capInsetsHeight": 1,
                  "capInsetsWidth": 1,
                  "capInsetsX": 0,
                  "capInsetsY": 0,
                  "fileName": null,
                  "fileNameData": {
                    "path": "7wan.png",
                    "plistFile": "majiangtu/majiang_pai_wenzi.plist",
                    "resourceType": 1
                  },
                  "scale9Enable": false,
                  "scale9Height": 114,
                  "scale9Width": 82
                }
              }
            ],
            "options": {
              "__type": "ImageViewSurrogate:#EditorCommon.JsonModel.Component.GUI",
              "classname": "ImageView",
              "name": "c10",
              "ZOrder": 0,
              "actiontag": 35300178,
              "anchorPointX": 0.5,
              "anchorPointY": 0.5,
              "classType": "CocoStudio.EngineAdapterWrap.CSImageView",
              "colorB": 255,
              "colorG": 255,
              "colorR": 255,
              "customProperty": "",
              "flipX": true,
              "flipY": false,
              "height": 55,
              "ignoreSize": true,
              "layoutParameter": null,
              "opacity": 255,
              "positionPercentX": 0.186666667,
              "positionPercentY": -0.238,
              "positionType": 0,
              "rotation": 0,
              "scaleX": 1.09,
              "scaleY": 1.09,
              "sizePercentX": 0.49333334,
              "sizePercentY": 0.11,
              "sizeType": 0,
              "tag": 185252,
              "touchAble": false,
              "useMergedTexture": false,
              "visible": true,
              "width": 74,
              "x": 28,
              "y": -119,
              "capInsetsHeight": 1,
              "capInsetsWidth": 1,
              "capInsetsX": 0,
              "capInsetsY": 0,
              "fileName": null,
              "fileNameData": {
                "path": "majiang_pai_sj_hp_00.png",
                "plistFile": "majiangtu/majiang_pai02.plist",
                "resourceType": 1
              },
              "scale9Enable": false,
              "scale9Height": 55,
              "scale9Width": 74
            }
          },
          {
            "classname": "ImageView",
            "name": null,
            "children": [
              {
                "classname": "ImageView",
                "name": null,
                "children": [],
                "options": {
                  "__type": "ImageViewSurrogate:#EditorCommon.JsonModel.Component.GUI",
                  "classname": "ImageView",
                  "name": "sv",
                  "ZOrder": 0,
                  "actiontag": 31134999,
                  "anchorPointX": 0.5,
                  "anchorPointY": 0.5,
                  "classType": "CocoStudio.EngineAdapterWrap.CSImageView",
                  "colorB": 255,
                  "colorG": 255,
                  "colorR": 255,
                  "customProperty": "",
                  "flipX": true,
                  "flipY": false,
                  "height": 114,
                  "ignoreSize": true,
                  "layoutParameter": null,
                  "opacity": 255,
                  "positionPercentX": 0.08108108,
                  "positionPercentY": 0.218181819,
                  "positionType": 0,
                  "rotation": 90,
                  "scaleX": 0.4,
                  "scaleY": 0.6,
                  "sizePercentX": 1.10810816,
                  "sizePercentY": 2.0727272,
                  "sizeType": 0,
                  "tag": 185255,
                  "touchAble": false,
                  "useMergedTexture": false,
                  "visible": true,
                  "width": 82,
                  "x": 6,
                  "y": 12,
                  "capInsetsHeight": 1,
                  "capInsetsWidth": 1,
                  "capInsetsX": 0,
                  "capInsetsY": 0,
                  "fileName": null,
                  "fileNameData": {
                    "path": "7wan.png",
                    "plistFile": "majiangtu/majiang_pai_wenzi.plist",
                    "resourceType": 1
                  },
                  "scale9Enable": false,
                  "scale9Height": 114,
                  "scale9Width": 82
                }
              }
            ],
            "options": {
              "__type": "ImageViewSurrogate:#EditorCommon.JsonModel.Component.GUI",
              "classname": "ImageView",
              "name": "c11",
              "ZOrder": 0,
              "actiontag": 40742146,
              "anchorPointX": 0.5,
              "anchorPointY": 0.5,
              "classType": "CocoStudio.EngineAdapterWrap.CSImageView",
              "colorB": 255,
              "colorG": 255,
              "colorR": 255,
              "customProperty": "",
              "flipX": true,
              "flipY": false,
              "height": 55,
              "ignoreSize": true,
              "layoutParameter": null,
              "opacity": 255,
              "positionPercentX": 0.24666667,
              "positionPercentY": -0.32,
              "positionType": 0,
              "rotation": 0,
              "scaleX": 1.1,
              "scaleY": 1.1,
              "sizePercentX": 0.49333334,
              "sizePercentY": 0.11,
              "sizeType": 0,
              "tag": 185254,
              "touchAble": false,
              "useMergedTexture": false,
              "visible": true,
              "width": 74,
              "x": 37,
              "y": -160,
              "capInsetsHeight": 1,
              "capInsetsWidth": 1,
              "capInsetsX": 0,
              "capInsetsY": 0,
              "fileName": null,
              "fileNameData": {
                "path": "majiang_pai_sj_hp_00.png",
                "plistFile": "majiangtu/majiang_pai02.plist",
                "resourceType": 1
              },
              "scale9Enable": false,
              "scale9Height": 55,
              "scale9Width": 74
            }
          },
          {
            "classname": "ImageView",
            "name": null,
            "children": [
              {
                "classname": "ImageView",
                "name": null,
                "children": [],
                "options": {
                  "__type": "ImageViewSurrogate:#EditorCommon.JsonModel.Component.GUI",
                  "classname": "ImageView",
                  "name": "sv",
                  "ZOrder": 0,
                  "actiontag": 38906991,
                  "anchorPointX": 0.5,
                  "anchorPointY": 0.5,
                  "classType": "CocoStudio.EngineAdapterWrap.CSImageView",
                  "colorB": 255,
                  "colorG": 255,
                  "colorR": 255,
                  "customProperty": "",
                  "flipX": true,
                  "flipY": false,
                  "height": 114,
                  "ignoreSize": true,
                  "layoutParameter": null,
                  "opacity": 255,
                  "positionPercentX": 0.08108108,
                  "positionPercentY": 0.218181819,
                  "positionType": 0,
                  "rotation": 90,
                  "scaleX": 0.4,
                  "scaleY": 0.6,
                  "sizePercentX": 1.10810816,
                  "sizePercentY": 2.0727272,
                  "sizeType": 0,
                  "tag": 185257,
                  "touchAble": false,
                  "useMergedTexture": false,
                  "visible": true,
                  "width": 82,
                  "x": 6,
                  "y": 12,
                  "capInsetsHeight": 1,
                  "capInsetsWidth": 1,
                  "capInsetsX": 0,
                  "capInsetsY": 0,
                  "fileName": null,
                  "fileNameData": {
                    "path": "7wan.png",
                    "plistFile": "majiangtu/majiang_pai_wenzi.plist",
                    "resourceType": 1
                  },
                  "scale9Enable": false,
                  "scale9Height": 114,
                  "scale9Width": 82
                }
              }
            ],
            "options": {
              "__type": "ImageViewSurrogate:#EditorCommon.JsonModel.Component.GUI",
              "classname": "ImageView",
              "name": "c12",
              "ZOrder": 0,
              "actiontag": 11779539,
              "anchorPointX": 0.5,
              "anchorPointY": 0.5,
              "classType": "CocoStudio.EngineAdapterWrap.CSImageView",
              "colorB": 255,
              "colorG": 255,
              "colorR": 255,
              "customProperty": "",
              "flipX": true,
              "flipY": false,
              "height": 55,
              "ignoreSize": true,
              "layoutParameter": null,
              "opacity": 255,
              "positionPercentX": 0.306666672,
              "positionPercentY": -0.4,
              "positionType": 0,
              "rotation": 0,
              "scaleX": 1.11,
              "scaleY": 1.11,
              "sizePercentX": 0.49333334,
              "sizePercentY": 0.11,
              "sizeType": 0,
              "tag": 185256,
              "touchAble": false,
              "useMergedTexture": false,
              "visible": true,
              "width": 74,
              "x": 46,
              "y": -200,
              "capInsetsHeight": 1,
              "capInsetsWidth": 1,
              "capInsetsX": 0,
              "capInsetsY": 0,
              "fileName": null,
              "fileNameData": {
                "path": "majiang_pai_sj_hp_00.png",
                "plistFile": "majiangtu/majiang_pai02.plist",
                "resourceType": 1
              },
              "scale9Enable": false,
              "scale9Height": 55,
              "scale9Width": 74
            }
          },
          {
            "classname": "ImageView",
            "name": null,
            "children": [
              {
                "classname": "ImageView",
                "name": null,
                "children": [],
                "options": {
                  "__type": "ImageViewSurrogate:#EditorCommon.JsonModel.Component.GUI",
                  "classname": "ImageView",
                  "name": "sv",
                  "ZOrder": 0,
                  "actiontag": 64458580,
                  "anchorPointX": 0.5,
                  "anchorPointY": 0.5,
                  "classType": "CocoStudio.EngineAdapterWrap.CSImageView",
                  "colorB": 255,
                  "colorG": 255,
                  "colorR": 255,
                  "customProperty": "",
                  "flipX": true,
                  "flipY": false,
                  "height": 114,
                  "ignoreSize": true,
                  "layoutParameter": null,
                  "opacity": 255,
                  "positionPercentX": 0.08108108,
                  "positionPercentY": 0.218181819,
                  "positionType": 0,
                  "rotation": 90,
                  "scaleX": 0.4,
                  "scaleY": 0.6,
                  "sizePercentX": 1.10810816,
                  "sizePercentY": 2.0727272,
                  "sizeType": 0,
                  "tag": 185259,
                  "touchAble": false,
                  "useMergedTexture": false,
                  "visible": true,
                  "width": 82,
                  "x": 6,
                  "y": 12,
                  "capInsetsHeight": 1,
                  "capInsetsWidth": 1,
                  "capInsetsX": 0,
                  "capInsetsY": 0,
                  "fileName": null,
                  "fileNameData": {
                    "path": "7wan.png",
                    "plistFile": "majiangtu/majiang_pai_wenzi.plist",
                    "resourceType": 1
                  },
                  "scale9Enable": false,
                  "scale9Height": 114,
                  "scale9Width": 82
                }
              }
            ],
            "options": {
              "__type": "ImageViewSurrogate:#EditorCommon.JsonModel.Component.GUI",
              "classname": "ImageView",
              "name": "c13",
              "ZOrder": 0,
              "actiontag": 14618604,
              "anchorPointX": 0.5,
              "anchorPointY": 0.5,
              "classType": "CocoStudio.EngineAdapterWrap.CSImageView",
              "colorB": 255,
              "colorG": 255,
              "colorR": 255,
              "customProperty": "",
              "flipX": true,
              "flipY": false,
              "height": 55,
              "ignoreSize": true,
              "layoutParameter": null,
              "opacity": 255,
              "positionPercentX": 0.373333335,
              "positionPercentY": -0.482,
              "positionType": 0,
              "rotation": 0,
              "scaleX": 1.12,
              "scaleY": 1.12,
              "sizePercentX": 0.49333334,
              "sizePercentY": 0.11,
              "sizeType": 0,
              "tag": 185258,
              "touchAble": false,
              "useMergedTexture": false,
              "visible": true,
              "width": 74,
              "x": 56,
              "y": -241,
              "capInsetsHeight": 1,
              "capInsetsWidth": 1,
              "capInsetsX": 0,
              "capInsetsY": 0,
              "fileName": null,
              "fileNameData": {
                "path": "majiang_pai_sj_hp_00.png",
                "plistFile": "majiangtu/majiang_pai02.plist",
                "resourceType": 1
              },
              "scale9Enable": false,
              "scale9Height": 55,
              "scale9Width": 74
            }
          },
          {
            "classname": "ImageView",
            "name": null,
            "children": [
              {
                "classname": "ImageView",
                "name": null,
                "children": [],
                "options": {
                  "__type": "ImageViewSurrogate:#EditorCommon.JsonModel.Component.GUI",
                  "classname": "ImageView",
                  "name": "sv",
                  "ZOrder": 0,
                  "actiontag": 53762477,
                  "anchorPointX": 0.5,
                  "anchorPointY": 0.5,
                  "classType": "CocoStudio.EngineAdapterWrap.CSImageView",
                  "colorB": 255,
                  "colorG": 255,
                  "colorR": 255,
                  "customProperty": "",
                  "flipX": true,
                  "flipY": false,
                  "height": 114,
                  "ignoreSize": true,
                  "layoutParameter": null,
                  "opacity": 255,
                  "positionPercentX": 0.08108108,
                  "positionPercentY": 0.218181819,
                  "positionType": 0,
                  "rotation": 90,
                  "scaleX": 0.4,
                  "scaleY": 0.6,
                  "sizePercentX": 1.10810816,
                  "sizePercentY": 2.0727272,
                  "sizeType": 0,
                  "tag": 185261,
                  "touchAble": false,
                  "useMergedTexture": false,
                  "visible": true,
                  "width": 82,
                  "x": 6,
                  "y": 12,
                  "capInsetsHeight": 1,
                  "capInsetsWidth": 1,
                  "capInsetsX": 0,
                  "capInsetsY": 0,
                  "fileName": null,
                  "fileNameData": {
                    "path": "7wan.png",
                    "plistFile": "majiangtu/majiang_pai_wenzi.plist",
                    "resourceType": 1
                  },
                  "scale9Enable": false,
                  "scale9Height": 114,
                  "scale9Width": 82
                }
              }
            ],
            "options": {
              "__type": "ImageViewSurrogate:#EditorCommon.JsonModel.Component.GUI",
              "classname": "ImageView",
              "name": "c14",
              "ZOrder": 0,
              "actiontag": 43256310,
              "anchorPointX": 0.5,
              "anchorPointY": 0.5,
              "classType": "CocoStudio.EngineAdapterWrap.CSImageView",
              "colorB": 255,
              "colorG": 255,
              "colorR": 255,
              "customProperty": "",
              "flipX": true,
              "flipY": false,
              "height": 55,
              "ignoreSize": true,
              "layoutParameter": null,
              "opacity": 255,
              "positionPercentX": 0.44,
              "positionPercentY": -0.562,
              "positionType": 0,
              "rotation": 0,
              "scaleX": 1.12,
              "scaleY": 1.12,
              "sizePercentX": 0.49333334,
              "sizePercentY": 0.11,
              "sizeType": 0,
              "tag": 185260,
              "touchAble": false,
              "useMergedTexture": false,
              "visible": true,
              "width": 74,
              "x": 66,
              "y": -281,
              "capInsetsHeight": 1,
              "capInsetsWidth": 1,
              "capInsetsX": 0,
              "capInsetsY": 0,
              "fileName": null,
              "fileNameData": {
                "path": "majiang_pai_sj_hp_00.png",
                "plistFile": "majiangtu/majiang_pai02.plist",
                "resourceType": 1
              },
              "scale9Enable": false,
              "scale9Height": 55,
              "scale9Width": 74
            }
          }
        ],
        "options": {
          "__type": "ImageViewSurrogate:#EditorCommon.JsonModel.Component.GUI",
          "classname": "ImageView",
          "name": "hubg",
          "ZOrder": 0,
          "actiontag": 18699405,
          "anchorPointX": 0.5,
          "anchorPointY": 0.5,
          "classType": "CocoStudio.EngineAdapterWrap.CSImageView",
          "colorB": 255,
          "colorG": 255,
          "colorR": 255,
          "customProperty": "",
          "flipX": false,
          "flipY": false,
          "height": 500,
          "ignoreSize": false,
          "layoutParameter": null,
          "opacity": 255,
          "positionPercentX": 0.827343762,
          "positionPercentY": 0.565277755,
          "positionType": 0,
          "rotation": -1,
          "scaleX": 0.799999952,
          "scaleY": 0.799999952,
          "sizePercentX": 0.1171875,
          "sizePercentY": 0.6944444,
          "sizeType": 0,
          "tag": 185233,
          "touchAble": false,
          "useMergedTexture": false,
          "visible": true,
          "width": 150,
          "x": 1059,
          "y": 407,
          "capInsetsHeight": 1,
          "capInsetsWidth": 1,
          "capInsetsX": 0,
          "capInsetsY": 0,
          "fileName": null,
          "fileNameData": {
            "path": "touming.png",
            "plistFile": "",
            "resourceType": 0
          },
          "scale9Enable": false,
          "scale9Height": 500,
          "scale9Width": 150
        }
      }
    ],
    "options": {
      "__type": "PanelSurrogate:#EditorCommon.JsonModel.Component.GUI",
      "classname": "Panel",
      "name": "Panel_224",
      "ZOrder": 0,
      "actiontag": -1,
      "anchorPointX": 0,
      "anchorPointY": 0,
      "classType": "CocoStudio.EngineAdapterWrap.CSPanel",
      "colorB": 255,
      "colorG": 255,
      "colorR": 255,
      "customProperty": "",
      "flipX": false,
      "flipY": false,
      "height": 720,
      "ignoreSize": false,
      "layoutParameter": null,
      "opacity": 255,
      "positionPercentX": 0,
      "positionPercentY": 0,
      "positionType": 0,
      "rotation": 0,
      "scaleX": 1,
      "scaleY": 1,
      "sizePercentX": 1,
      "sizePercentY": 1,
      "sizeType": 0,
      "tag": 185023,
      "touchAble": false,
      "useMergedTexture": false,
      "visible": true,
      "width": 1280,
      "x": 0,
      "y": 0,
      "adaptScreen": false,
      "backGroundImage": null,
      "backGroundImageData": null,
      "backGroundScale9Enable": false,
      "bgColorB": 255,
      "bgColorG": 200,
      "bgColorOpacity": 0,
      "bgColorR": 150,
      "bgEndColorB": 255,
      "bgEndColorG": 200,
      "bgEndColorR": 150,
      "bgStartColorB": 255,
      "bgStartColorG": 255,
      "bgStartColorR": 255,
      "capInsetsHeight": 1,
      "capInsetsWidth": 1,
      "capInsetsX": 0,
      "capInsetsY": 0,
      "clipAble": false,
      "colorType": 1,
      "layoutType": 0,
      "vectorX": 0,
      "vectorY": -0.5
    }
  }
}