{
  "classname": null,
  "name": null,
  "animation": {
    "classname": null,
    "name": "AnimationManager",
    "actionlist": []
  },
  "dataScale": 1,
  "designHeight": 720,
  "designWidth": 1280,
  "textures": [
    "majiangtu/majiang_pai.plist"
  ],
  "texturesPng": [
    "touming.png",
    "majiangtu/majiang_pai.plist"
  ],
  "version": "1.6.0.0",
  "widgetTree": {
    "classname": "Panel",
    "name": null,
    "children": [
      {
        "classname": "ImageView",
        "name": null,
        "children": [
          {
            "classname": "ImageView",
            "name": null,
            "children": [],
            "options": {
              "__type": "ImageViewSurrogate:#EditorCommon.JsonModel.Component.GUI",
              "classname": "ImageView",
              "name": "lp2",
              "ZOrder": 15,
              "actiontag": 15468616,
              "anchorPointX": 0.5,
              "anchorPointY": 0.5,
              "classType": "CocoStudio.EngineAdapterWrap.CSImageView",
              "colorB": 255,
              "colorG": 255,
              "colorR": 255,
              "customProperty": "",
              "flipX": true,
              "flipY": false,
              "height": 46,
              "ignoreSize": true,
              "layoutParameter": null,
              "opacity": 255,
              "positionPercentX": 0.28125,
              "positionPercentY": -0.425055921,
              "positionType": 0,
              "rotation": 0,
              "scaleX": 1,
              "scaleY": 1,
              "sizePercentX": 0.3875,
              "sizePercentY": 0.102908276,
              "sizeType": 0,
              "tag": 185491,
              "touchAble": false,
              "useMergedTexture": false,
              "visible": true,
              "width": 62,
              "x": 45,
              "y": -190,
              "capInsetsHeight": 1,
              "capInsetsWidth": 1,
              "capInsetsX": 0,
              "capInsetsY": 0,
              "fileName": null,
              "fileNameData": {
                "path": "majiang_pai_pq_sj_00.png",
                "plistFile": "majiangtu/majiang_pai.plist",
                "resourceType": 1
              },
              "scale9Enable": false,
              "scale9Height": 46,
              "scale9Width": 62
            }
          },
          {
            "classname": "ImageView",
            "name": null,
            "children": [],
            "options": {
              "__type": "ImageViewSurrogate:#EditorCommon.JsonModel.Component.GUI",
              "classname": "ImageView",
              "name": "lp4",
              "ZOrder": 13,
              "actiontag": 44998406,
              "anchorPointX": 0.5,
              "anchorPointY": 0.5,
              "classType": "CocoStudio.EngineAdapterWrap.CSImageView",
              "colorB": 255,
              "colorG": 255,
              "colorR": 255,
              "customProperty": "",
              "flipX": true,
              "flipY": false,
              "height": 45,
              "ignoreSize": true,
              "layoutParameter": null,
              "opacity": 255,
              "positionPercentX": 0.2375,
              "positionPercentY": -0.353467554,
              "positionType": 0,
              "rotation": 0,
              "scaleX": 1,
              "scaleY": 1,
              "sizePercentX": 0.38125,
              "sizePercentY": 0.100671142,
              "sizeType": 0,
              "tag": 185492,
              "touchAble": false,
              "useMergedTexture": false,
              "visible": true,
              "width": 61,
              "x": 38,
              "y": -158,
              "capInsetsHeight": 1,
              "capInsetsWidth": 1,
              "capInsetsX": 0,
              "capInsetsY": 0,
              "fileName": null,
              "fileNameData": {
                "path": "majiang_pai_pq_sj_02.png",
                "plistFile": "majiangtu/majiang_pai.plist",
                "resourceType": 1
              },
              "scale9Enable": false,
              "scale9Height": 45,
              "scale9Width": 61
            }
          },
          {
            "classname": "ImageView",
            "name": null,
            "children": [],
            "options": {
              "__type": "ImageViewSurrogate:#EditorCommon.JsonModel.Component.GUI",
              "classname": "ImageView",
              "name": "lp6",
              "ZOrder": 12,
              "actiontag": 2332471,
              "anchorPointX": 0.5,
              "anchorPointY": 0.5,
              "classType": "CocoStudio.EngineAdapterWrap.CSImageView",
              "colorB": 255,
              "colorG": 255,
              "colorR": 255,
              "customProperty": "",
              "flipX": true,
              "flipY": false,
              "height": 44,
              "ignoreSize": true,
              "layoutParameter": null,
              "opacity": 255,
              "positionPercentX": 0.2,
              "positionPercentY": -0.286353469,
              "positionType": 0,
              "rotation": 0,
              "scaleX": 1,
              "scaleY": 1,
              "sizePercentX": 0.375,
              "sizePercentY": 0.098434,
              "sizeType": 0,
              "tag": 185493,
              "touchAble": false,
              "useMergedTexture": false,
              "visible": true,
              "width": 60,
              "x": 32,
              "y": -128,
              "capInsetsHeight": 1,
              "capInsetsWidth": 1,
              "capInsetsX": 0,
              "capInsetsY": 0,
              "fileName": null,
              "fileNameData": {
                "path": "majiang_pai_pq_sj_04.png",
                "plistFile": "majiangtu/majiang_pai.plist",
                "resourceType": 1
              },
              "scale9Enable": false,
              "scale9Height": 44,
              "scale9Width": 60
            }
          },
          {
            "classname": "ImageView",
            "name": null,
            "children": [],
            "options": {
              "__type": "ImageViewSurrogate:#EditorCommon.JsonModel.Component.GUI",
              "classname": "ImageView",
              "name": "lp8",
              "ZOrder": 11,
              "actiontag": 20992244,
              "anchorPointX": 0.5,
              "anchorPointY": 0.5,
              "classType": "CocoStudio.EngineAdapterWrap.CSImageView",
              "colorB": 255,
              "colorG": 255,
              "colorR": 255,
              "customProperty": "",
              "flipX": true,
              "flipY": false,
              "height": 43,
              "ignoreSize": true,
              "layoutParameter": null,
              "opacity": 255,
              "positionPercentX": 0.1625,
              "positionPercentY": -0.219239369,
              "positionType": 0,
              "rotation": 0,
              "scaleX": 1,
              "scaleY": 1,
              "sizePercentX": 0.3625,
              "sizePercentY": 0.09619687,
              "sizeType": 0,
              "tag": 185494,
              "touchAble": false,
              "useMergedTexture": false,
              "visible": true,
              "width": 58,
              "x": 26,
              "y": -98,
              "capInsetsHeight": 1,
              "capInsetsWidth": 1,
              "capInsetsX": 0,
              "capInsetsY": 0,
              "fileName": null,
              "fileNameData": {
                "path": "majiang_pai_pq_sj_06.png",
                "plistFile": "majiangtu/majiang_pai.plist",
                "resourceType": 1
              },
              "scale9Enable": false,
              "scale9Height": 43,
              "scale9Width": 58
            }
          },
          {
            "classname": "ImageView",
            "name": null,
            "children": [],
            "options": {
              "__type": "ImageViewSurrogate:#EditorCommon.JsonModel.Component.GUI",
              "classname": "ImageView",
              "name": "lp10",
              "ZOrder": 10,
              "actiontag": 54712468,
              "anchorPointX": 0.5,
              "anchorPointY": 0.5,
              "classType": "CocoStudio.EngineAdapterWrap.CSImageView",
              "colorB": 255,
              "colorG": 255,
              "colorR": 255,
              "customProperty": "",
              "flipX": true,
              "flipY": false,
              "height": 43,
              "ignoreSize": true,
              "layoutParameter": null,
              "opacity": 255,
              "positionPercentX": 0.125,
              "positionPercentY": -0.152125284,
              "positionType": 0,
              "rotation": 0,
              "scaleX": 1,
              "scaleY": 1,
              "sizePercentX": 0.3625,
              "sizePercentY": 0.09619687,
              "sizeType": 0,
              "tag": 185495,
              "touchAble": false,
              "useMergedTexture": false,
              "visible": true,
              "width": 58,
              "x": 20,
              "y": -68,
              "capInsetsHeight": 1,
              "capInsetsWidth": 1,
              "capInsetsX": 0,
              "capInsetsY": 0,
              "fileName": null,
              "fileNameData": {
                "path": "majiang_pai_pq_sj_08.png",
                "plistFile": "majiangtu/majiang_pai.plist",
                "resourceType": 1
              },
              "scale9Enable": false,
              "scale9Height": 43,
              "scale9Width": 58
            }
          },
          {
            "classname": "ImageView",
            "name": null,
            "children": [],
            "options": {
              "__type": "ImageViewSurrogate:#EditorCommon.JsonModel.Component.GUI",
              "classname": "ImageView",
              "name": "lp12",
              "ZOrder": 9,
              "actiontag": 22650170,
              "anchorPointX": 0.5,
              "anchorPointY": 0.5,
              "classType": "CocoStudio.EngineAdapterWrap.CSImageView",
              "colorB": 255,
              "colorG": 255,
              "colorR": 255,
              "customProperty": "",
              "flipX": true,
              "flipY": false,
              "height": 42,
              "ignoreSize": true,
              "layoutParameter": null,
              "opacity": 255,
              "positionPercentX": 0.0875,
              "positionPercentY": -0.08948546,
              "positionType": 0,
              "rotation": 0,
              "scaleX": 1,
              "scaleY": 1,
              "sizePercentX": 0.35625,
              "sizePercentY": 0.0939597338,
              "sizeType": 0,
              "tag": 185496,
              "touchAble": false,
              "useMergedTexture": false,
              "visible": true,
              "width": 57,
              "x": 14,
              "y": -40,
              "capInsetsHeight": 1,
              "capInsetsWidth": 1,
              "capInsetsX": 0,
              "capInsetsY": 0,
              "fileName": null,
              "fileNameData": {
                "path": "majiang_pai_pq_sj_10.png",
                "plistFile": "majiangtu/majiang_pai.plist",
                "resourceType": 1
              },
              "scale9Enable": false,
              "scale9Height": 42,
              "scale9Width": 57
            }
          },
          {
            "classname": "ImageView",
            "name": null,
            "children": [],
            "options": {
              "__type": "ImageViewSurrogate:#EditorCommon.JsonModel.Component.GUI",
              "classname": "ImageView",
              "name": "lp14",
              "ZOrder": 8,
              "actiontag": 2524942,
              "anchorPointX": 0.5,
              "anchorPointY": 0.5,
              "classType": "CocoStudio.EngineAdapterWrap.CSImageView",
              "colorB": 255,
              "colorG": 255,
              "colorR": 255,
              "customProperty": "",
              "flipX": true,
              "flipY": false,
              "height": 41,
              "ignoreSize": true,
              "layoutParameter": null,
              "opacity": 255,
              "positionPercentX": 0.05,
              "positionPercentY": -0.0268456377,
              "positionType": 0,
              "rotation": 0,
              "scaleX": 1,
              "scaleY": 1,
              "sizePercentX": 0.34375,
              "sizePercentY": 0.09172259,
              "sizeType": 0,
              "tag": 185497,
              "touchAble": false,
              "useMergedTexture": false,
              "visible": true,
              "width": 55,
              "x": 8,
              "y": -12,
              "capInsetsHeight": 1,
              "capInsetsWidth": 1,
              "capInsetsX": 0,
              "capInsetsY": 0,
              "fileName": null,
              "fileNameData": {
                "path": "majiang_pai_pq_sj_12.png",
                "plistFile": "majiangtu/majiang_pai.plist",
                "resourceType": 1
              },
              "scale9Enable": false,
              "scale9Height": 41,
              "scale9Width": 55
            }
          },
          {
            "classname": "ImageView",
            "name": null,
            "children": [],
            "options": {
              "__type": "ImageViewSurrogate:#EditorCommon.JsonModel.Component.GUI",
              "classname": "ImageView",
              "name": "lp16",
              "ZOrder": 7,
              "actiontag": 57366391,
              "anchorPointX": 0.5,
              "anchorPointY": 0.5,
              "classType": "CocoStudio.EngineAdapterWrap.CSImageView",
              "colorB": 255,
              "colorG": 255,
              "colorR": 255,
              "customProperty": "",
              "flipX": true,
              "flipY": false,
              "height": 40,
              "ignoreSize": true,
              "layoutParameter": null,
              "opacity": 255,
              "positionPercentX": 0.01875,
              "positionPercentY": 0.03131991,
              "positionType": 0,
              "rotation": 0,
              "scaleX": 1,
              "scaleY": 1,
              "sizePercentX": 0.3375,
              "sizePercentY": 0.08948546,
              "sizeType": 0,
              "tag": 185498,
              "touchAble": false,
              "useMergedTexture": false,
              "visible": true,
              "width": 54,
              "x": 3,
              "y": 14,
              "capInsetsHeight": 1,
              "capInsetsWidth": 1,
              "capInsetsX": 0,
              "capInsetsY": 0,
              "fileName": null,
              "fileNameData": {
                "path": "majiang_pai_pq_sj_14.png",
                "plistFile": "majiangtu/majiang_pai.plist",
                "resourceType": 1
              },
              "scale9Enable": false,
              "scale9Height": 40,
              "scale9Width": 54
            }
          },
          {
            "classname": "ImageView",
            "name": null,
            "children": [],
            "options": {
              "__type": "ImageViewSurrogate:#EditorCommon.JsonModel.Component.GUI",
              "classname": "ImageView",
              "name": "lp18",
              "ZOrder": 6,
              "actiontag": 34383282,
              "anchorPointX": 0.5,
              "anchorPointY": 0.5,
              "classType": "CocoStudio.EngineAdapterWrap.CSImageView",
              "colorB": 255,
              "colorG": 255,
              "colorR": 255,
              "customProperty": "",
              "flipX": true,
              "flipY": false,
              "height": 39,
              "ignoreSize": true,
              "layoutParameter": null,
              "opacity": 255,
              "positionPercentX": -0.01875,
              "positionPercentY": 0.08948546,
              "positionType": 0,
              "rotation": 0,
              "scaleX": 1,
              "scaleY": 1,
              "sizePercentX": 0.3375,
              "sizePercentY": 0.0872483253,
              "sizeType": 0,
              "tag": 185499,
              "touchAble": false,
              "useMergedTexture": false,
              "visible": true,
              "width": 54,
              "x": -3,
              "y": 40,
              "capInsetsHeight": 1,
              "capInsetsWidth": 1,
              "capInsetsX": 0,
              "capInsetsY": 0,
              "fileName": null,
              "fileNameData": {
                "path": "majiang_pai_pq_sj_16.png",
                "plistFile": "majiangtu/majiang_pai.plist",
                "resourceType": 1
              },
              "scale9Enable": false,
              "scale9Height": 39,
              "scale9Width": 54
            }
          },
          {
            "classname": "ImageView",
            "name": null,
            "children": [],
            "options": {
              "__type": "ImageViewSurrogate:#EditorCommon.JsonModel.Component.GUI",
              "classname": "ImageView",
              "name": "lp20",
              "ZOrder": 5,
              "actiontag": 41014082,
              "anchorPointX": 0.5,
              "anchorPointY": 0.5,
              "classType": "CocoStudio.EngineAdapterWrap.CSImageView",
              "colorB": 255,
              "colorG": 255,
              "colorR": 255,
              "customProperty": "",
              "flipX": true,
              "flipY": false,
              "height": 39,
              "ignoreSize": true,
              "layoutParameter": null,
              "opacity": 255,
              "positionPercentX": -0.05625,
              "positionPercentY": 0.145413876,
              "positionType": 0,
              "rotation": 0,
              "scaleX": 1,
              "scaleY": 1,
              "sizePercentX": 0.33125,
              "sizePercentY": 0.0872483253,
              "sizeType": 0,
              "tag": 185500,
              "touchAble": false,
              "useMergedTexture": false,
              "visible": true,
              "width": 53,
              "x": -9,
              "y": 65,
              "capInsetsHeight": 1,
              "capInsetsWidth": 1,
              "capInsetsX": 0,
              "capInsetsY": 0,
              "fileName": null,
              "fileNameData": {
                "path": "majiang_pai_pq_sj_18.png",
                "plistFile": "majiangtu/majiang_pai.plist",
                "resourceType": 1
              },
              "scale9Enable": false,
              "scale9Height": 39,
              "scale9Width": 53
            }
          },
          {
            "classname": "ImageView",
            "name": null,
            "children": [],
            "options": {
              "__type": "ImageViewSurrogate:#EditorCommon.JsonModel.Component.GUI",
              "classname": "ImageView",
              "name": "lp22",
              "ZOrder": 4,
              "actiontag": 33582418,
              "anchorPointX": 0.5,
              "anchorPointY": 0.5,
              "classType": "CocoStudio.EngineAdapterWrap.CSImageView",
              "colorB": 255,
              "colorG": 255,
              "colorR": 255,
              "customProperty": "",
              "flipX": true,
              "flipY": false,
              "height": 38,
              "ignoreSize": true,
              "layoutParameter": null,
              "opacity": 255,
              "positionPercentX": -0.08125,
              "positionPercentY": 0.199105144,
              "positionType": 0,
              "rotation": 0,
              "scaleX": 1,
              "scaleY": 1,
              "sizePercentX": 0.325,
              "sizePercentY": 0.0850111842,
              "sizeType": 0,
              "tag": 185501,
              "touchAble": false,
              "useMergedTexture": false,
              "visible": true,
              "width": 52,
              "x": -13,
              "y": 89,
              "capInsetsHeight": 1,
              "capInsetsWidth": 1,
              "capInsetsX": 0,
              "capInsetsY": 0,
              "fileName": null,
              "fileNameData": {
                "path": "majiang_pai_pq_sj_20.png",
                "plistFile": "majiangtu/majiang_pai.plist",
                "resourceType": 1
              },
              "scale9Enable": false,
              "scale9Height": 38,
              "scale9Width": 52
            }
          },
          {
            "classname": "ImageView",
            "name": null,
            "children": [],
            "options": {
              "__type": "ImageViewSurrogate:#EditorCommon.JsonModel.Component.GUI",
              "classname": "ImageView",
              "name": "lp24",
              "ZOrder": 3,
              "actiontag": 33806307,
              "anchorPointX": 0.5,
              "anchorPointY": 0.5,
              "classType": "CocoStudio.EngineAdapterWrap.CSImageView",
              "colorB": 255,
              "colorG": 255,
              "colorR": 255,
              "customProperty": "",
              "flipX": true,
              "flipY": false,
              "height": 37,
              "ignoreSize": true,
              "layoutParameter": null,
              "opacity": 255,
              "positionPercentX": -0.1125,
              "positionPercentY": 0.2527964,
              "positionType": 0,
              "rotation": 0,
              "scaleX": 1,
              "scaleY": 1,
              "sizePercentX": 0.325,
              "sizePercentY": 0.08277405,
              "sizeType": 0,
              "tag": 185502,
              "touchAble": false,
              "useMergedTexture": false,
              "visible": true,
              "width": 52,
              "x": -18,
              "y": 113,
              "capInsetsHeight": 1,
              "capInsetsWidth": 1,
              "capInsetsX": 0,
              "capInsetsY": 0,
              "fileName": null,
              "fileNameData": {
                "path": "majiang_pai_pq_sj_22.png",
                "plistFile": "majiangtu/majiang_pai.plist",
                "resourceType": 1
              },
              "scale9Enable": false,
              "scale9Height": 37,
              "scale9Width": 52
            }
          },
          {
            "classname": "ImageView",
            "name": null,
            "children": [],
            "options": {
              "__type": "ImageViewSurrogate:#EditorCommon.JsonModel.Component.GUI",
              "classname": "ImageView",
              "name": "lp26",
              "ZOrder": 2,
              "actiontag": 35821310,
              "anchorPointX": 0.5,
              "anchorPointY": 0.5,
              "classType": "CocoStudio.EngineAdapterWrap.CSImageView",
              "colorB": 255,
              "colorG": 255,
              "colorR": 255,
              "customProperty": "",
              "flipX": true,
              "flipY": false,
              "height": 37,
              "ignoreSize": true,
              "layoutParameter": null,
              "opacity": 255,
              "positionPercentX": -0.14375,
              "positionPercentY": 0.304250568,
              "positionType": 0,
              "rotation": 0,
              "scaleX": 1,
              "scaleY": 1,
              "sizePercentX": 0.3125,
              "sizePercentY": 0.08277405,
              "sizeType": 0,
              "tag": 185503,
              "touchAble": false,
              "useMergedTexture": false,
              "visible": true,
              "width": 50,
              "x": -23,
              "y": 136,
              "capInsetsHeight": 1,
              "capInsetsWidth": 1,
              "capInsetsX": 0,
              "capInsetsY": 0,
              "fileName": null,
              "fileNameData": {
                "path": "majiang_pai_pq_sj_24.png",
                "plistFile": "majiangtu/majiang_pai.plist",
                "resourceType": 1
              },
              "scale9Enable": false,
              "scale9Height": 37,
              "scale9Width": 50
            }
          },
          {
            "classname": "ImageView",
            "name": null,
            "children": [],
            "options": {
              "__type": "ImageViewSurrogate:#EditorCommon.JsonModel.Component.GUI",
              "classname": "ImageView",
              "name": "lp28",
              "ZOrder": 1,
              "actiontag": 53956341,
              "anchorPointX": 0.5,
              "anchorPointY": 0.5,
              "classType": "CocoStudio.EngineAdapterWrap.CSImageView",
              "colorB": 255,
              "colorG": 255,
              "colorR": 255,
              "customProperty": "",
              "flipX": true,
              "flipY": false,
              "height": 37,
              "ignoreSize": true,
              "layoutParameter": null,
              "opacity": 255,
              "positionPercentX": -0.16875,
              "positionPercentY": 0.357941836,
              "positionType": 0,
              "rotation": 0,
              "scaleX": 1,
              "scaleY": 1,
              "sizePercentX": 0.30625,
              "sizePercentY": 0.08277405,
              "sizeType": 0,
              "tag": 185504,
              "touchAble": false,
              "useMergedTexture": false,
              "visible": true,
              "width": 49,
              "x": -27,
              "y": 160,
              "capInsetsHeight": 1,
              "capInsetsWidth": 1,
              "capInsetsX": 0,
              "capInsetsY": 0,
              "fileName": null,
              "fileNameData": {
                "path": "majiang_pai_pq_sj_26.png",
                "plistFile": "majiangtu/majiang_pai.plist",
                "resourceType": 1
              },
              "scale9Enable": false,
              "scale9Height": 37,
              "scale9Width": 49
            }
          },
          {
            "classname": "ImageView",
            "name": null,
            "children": [],
            "options": {
              "__type": "ImageViewSurrogate:#EditorCommon.JsonModel.Component.GUI",
              "classname": "ImageView",
              "name": "lp30",
              "ZOrder": 0,
              "actiontag": 15845023,
              "anchorPointX": 0.5,
              "anchorPointY": 0.5,
              "classType": "CocoStudio.EngineAdapterWrap.CSImageView",
              "colorB": 255,
              "colorG": 255,
              "colorR": 255,
              "customProperty": "",
              "flipX": true,
              "flipY": false,
              "height": 36,
              "ignoreSize": true,
              "layoutParameter": null,
              "opacity": 255,
              "positionPercentX": -0.19375,
              "positionPercentY": 0.407158822,
              "positionType": 0,
              "rotation": 0,
              "scaleX": 1,
              "scaleY": 1,
              "sizePercentX": 0.30625,
              "sizePercentY": 0.08053691,
              "sizeType": 0,
              "tag": 185505,
              "touchAble": false,
              "useMergedTexture": false,
              "visible": true,
              "width": 49,
              "x": -31,
              "y": 182,
              "capInsetsHeight": 1,
              "capInsetsWidth": 1,
              "capInsetsX": 0,
              "capInsetsY": 0,
              "fileName": null,
              "fileNameData": {
                "path": "majiang_pai_pq_sj_28.png",
                "plistFile": "majiangtu/majiang_pai.plist",
                "resourceType": 1
              },
              "scale9Enable": false,
              "scale9Height": 36,
              "scale9Width": 49
            }
          },
          {
            "classname": "ImageView",
            "name": null,
            "children": [],
            "options": {
              "__type": "ImageViewSurrogate:#EditorCommon.JsonModel.Component.GUI",
              "classname": "ImageView",
              "name": "lp1",
              "ZOrder": 15,
              "actiontag": 8387487,
              "anchorPointX": 0.5,
              "anchorPointY": 0.5,
              "classType": "CocoStudio.EngineAdapterWrap.CSImageView",
              "colorB": 255,
              "colorG": 255,
              "colorR": 255,
              "customProperty": "",
              "flipX": true,
              "flipY": false,
              "height": 45,
              "ignoreSize": true,
              "layoutParameter": null,
              "opacity": 255,
              "positionPercentX": 0.3125,
              "positionPercentY": -0.3870246,
              "positionType": 0,
              "rotation": 0,
              "scaleX": 1,
              "scaleY": 1,
              "sizePercentX": 0.38125,
              "sizePercentY": 0.100671142,
              "sizeType": 0,
              "tag": 185506,
              "touchAble": false,
              "useMergedTexture": false,
              "visible": true,
              "width": 61,
              "x": 50,
              "y": -173,
              "capInsetsHeight": 1,
              "capInsetsWidth": 1,
              "capInsetsX": 0,
              "capInsetsY": 0,
              "fileName": null,
              "fileNameData": {
                "path": "majiang_pai_pq_sj_01.png",
                "plistFile": "majiangtu/majiang_pai.plist",
                "resourceType": 1
              },
              "scale9Enable": false,
              "scale9Height": 45,
              "scale9Width": 61
            }
          },
          {
            "classname": "ImageView",
            "name": null,
            "children": [],
            "options": {
              "__type": "ImageViewSurrogate:#EditorCommon.JsonModel.Component.GUI",
              "classname": "ImageView",
              "name": "lp3",
              "ZOrder": 13,
              "actiontag": 8378525,
              "anchorPointX": 0.5,
              "anchorPointY": 0.5,
              "classType": "CocoStudio.EngineAdapterWrap.CSImageView",
              "colorB": 255,
              "colorG": 255,
              "colorR": 255,
              "customProperty": "",
              "flipX": true,
              "flipY": false,
              "height": 45,
              "ignoreSize": true,
              "layoutParameter": null,
              "opacity": 255,
              "positionPercentX": 0.275,
              "positionPercentY": -0.315436244,
              "positionType": 0,
              "rotation": 0,
              "scaleX": 1,
              "scaleY": 1,
              "sizePercentX": 0.38125,
              "sizePercentY": 0.100671142,
              "sizeType": 0,
              "tag": 185507,
              "touchAble": false,
              "useMergedTexture": false,
              "visible": true,
              "width": 61,
              "x": 44,
              "y": -141,
              "capInsetsHeight": 1,
              "capInsetsWidth": 1,
              "capInsetsX": 0,
              "capInsetsY": 0,
              "fileName": null,
              "fileNameData": {
                "path": "majiang_pai_pq_sj_02.png",
                "plistFile": "majiangtu/majiang_pai.plist",
                "resourceType": 1
              },
              "scale9Enable": false,
              "scale9Height": 45,
              "scale9Width": 61
            }
          },
          {
            "classname": "ImageView",
            "name": null,
            "children": [],
            "options": {
              "__type": "ImageViewSurrogate:#EditorCommon.JsonModel.Component.GUI",
              "classname": "ImageView",
              "name": "lp5",
              "ZOrder": 12,
              "actiontag": 8297866,
              "anchorPointX": 0.5,
              "anchorPointY": 0.5,
              "classType": "CocoStudio.EngineAdapterWrap.CSImageView",
              "colorB": 255,
              "colorG": 255,
              "colorR": 255,
              "customProperty": "",
              "flipX": true,
              "flipY": false,
              "height": 44,
              "ignoreSize": true,
              "layoutParameter": null,
              "opacity": 255,
              "positionPercentX": 0.23125,
              "positionPercentY": -0.248322144,
              "positionType": 0,
              "rotation": 0,
              "scaleX": 1,
              "scaleY": 1,
              "sizePercentX": 0.375,
              "sizePercentY": 0.098434,
              "sizeType": 0,
              "tag": 185508,
              "touchAble": false,
              "useMergedTexture": false,
              "visible": true,
              "width": 60,
              "x": 37,
              "y": -111,
              "capInsetsHeight": 1,
              "capInsetsWidth": 1,
              "capInsetsX": 0,
              "capInsetsY": 0,
              "fileName": null,
              "fileNameData": {
                "path": "majiang_pai_pq_sj_04.png",
                "plistFile": "majiangtu/majiang_pai.plist",
                "resourceType": 1
              },
              "scale9Enable": false,
              "scale9Height": 44,
              "scale9Width": 60
            }
          },
          {
            "classname": "ImageView",
            "name": null,
            "children": [],
            "options": {
              "__type": "ImageViewSurrogate:#EditorCommon.JsonModel.Component.GUI",
              "classname": "ImageView",
              "name": "lp7",
              "ZOrder": 11,
              "actiontag": 7571935,
              "anchorPointX": 0.5,
              "anchorPointY": 0.5,
              "classType": "CocoStudio.EngineAdapterWrap.CSImageView",
              "colorB": 255,
              "colorG": 255,
              "colorR": 255,
              "customProperty": "",
              "flipX": true,
              "flipY": false,
              "height": 43,
              "ignoreSize": true,
              "layoutParameter": null,
              "opacity": 255,
              "positionPercentX": 0.19375,
              "positionPercentY": -0.181208059,
              "positionType": 0,
              "rotation": 0,
              "scaleX": 1,
              "scaleY": 1,
              "sizePercentX": 0.3625,
              "sizePercentY": 0.09619687,
              "sizeType": 0,
              "tag": 185509,
              "touchAble": false,
              "useMergedTexture": false,
              "visible": true,
              "width": 58,
              "x": 31,
              "y": -81,
              "capInsetsHeight": 1,
              "capInsetsWidth": 1,
              "capInsetsX": 0,
              "capInsetsY": 0,
              "fileName": null,
              "fileNameData": {
                "path": "majiang_pai_pq_sj_06.png",
                "plistFile": "majiangtu/majiang_pai.plist",
                "resourceType": 1
              },
              "scale9Enable": false,
              "scale9Height": 43,
              "scale9Width": 58
            }
          },
          {
            "classname": "ImageView",
            "name": null,
            "children": [],
            "options": {
              "__type": "ImageViewSurrogate:#EditorCommon.JsonModel.Component.GUI",
              "classname": "ImageView",
              "name": "lp9",
              "ZOrder": 10,
              "actiontag": 1038558,
              "anchorPointX": 0.5,
              "anchorPointY": 0.5,
              "classType": "CocoStudio.EngineAdapterWrap.CSImageView",
              "colorB": 255,
              "colorG": 255,
              "colorR": 255,
              "customProperty": "",
              "flipX": true,
              "flipY": false,
              "height": 43,
              "ignoreSize": true,
              "layoutParameter": null,
              "opacity": 255,
              "positionPercentX": 0.15625,
              "positionPercentY": -0.114093959,
              "positionType": 0,
              "rotation": 0,
              "scaleX": 1,
              "scaleY": 1,
              "sizePercentX": 0.3625,
              "sizePercentY": 0.09619687,
              "sizeType": 0,
              "tag": 185510,
              "touchAble": false,
              "useMergedTexture": false,
              "visible": true,
              "width": 58,
              "x": 25,
              "y": -51,
              "capInsetsHeight": 1,
              "capInsetsWidth": 1,
              "capInsetsX": 0,
              "capInsetsY": 0,
              "fileName": null,
              "fileNameData": {
                "path": "majiang_pai_pq_sj_08.png",
                "plistFile": "majiangtu/majiang_pai.plist",
                "resourceType": 1
              },
              "scale9Enable": false,
              "scale9Height": 43,
              "scale9Width": 58
            }
          },
          {
            "classname": "ImageView",
            "name": null,
            "children": [],
            "options": {
              "__type": "ImageViewSurrogate:#EditorCommon.JsonModel.Component.GUI",
              "classname": "ImageView",
              "name": "lp11",
              "ZOrder": 9,
              "actiontag": 9347022,
              "anchorPointX": 0.5,
              "anchorPointY": 0.5,
              "classType": "CocoStudio.EngineAdapterWrap.CSImageView",
              "colorB": 255,
              "colorG": 255,
              "colorR": 255,
              "customProperty": "",
              "flipX": true,
              "flipY": false,
              "height": 42,
              "ignoreSize": true,
              "layoutParameter": null,
              "opacity": 255,
              "positionPercentX": 0.11875,
              "positionPercentY": -0.051454138,
              "positionType": 0,
              "rotation": 0,
              "scaleX": 1,
              "scaleY": 1,
              "sizePercentX": 0.35625,
              "sizePercentY": 0.0939597338,
              "sizeType": 0,
              "tag": 185511,
              "touchAble": false,
              "useMergedTexture": false,
              "visible": true,
              "width": 57,
              "x": 19,
              "y": -23,
              "capInsetsHeight": 1,
              "capInsetsWidth": 1,
              "capInsetsX": 0,
              "capInsetsY": 0,
              "fileName": null,
              "fileNameData": {
                "path": "majiang_pai_pq_sj_10.png",
                "plistFile": "majiangtu/majiang_pai.plist",
                "resourceType": 1
              },
              "scale9Enable": false,
              "scale9Height": 42,
              "scale9Width": 57
            }
          },
          {
            "classname": "ImageView",
            "name": null,
            "children": [],
            "options": {
              "__type": "ImageViewSurrogate:#EditorCommon.JsonModel.Component.GUI",
              "classname": "ImageView",
              "name": "lp13",
              "ZOrder": 8,
              "actiontag": 17014337,
              "anchorPointX": 0.5,
              "anchorPointY": 0.5,
              "classType": "CocoStudio.EngineAdapterWrap.CSImageView",
              "colorB": 255,
              "colorG": 255,
              "colorR": 255,
              "customProperty": "",
              "flipX": true,
              "flipY": false,
              "height": 41,
              "ignoreSize": true,
              "layoutParameter": null,
              "opacity": 255,
              "positionPercentX": 0.08125,
              "positionPercentY": 0.008948546,
              "positionType": 0,
              "rotation": 0,
              "scaleX": 1,
              "scaleY": 1,
              "sizePercentX": 0.34375,
              "sizePercentY": 0.09172259,
              "sizeType": 0,
              "tag": 185512,
              "touchAble": false,
              "useMergedTexture": false,
              "visible": true,
              "width": 55,
              "x": 13,
              "y": 4,
              "capInsetsHeight": 1,
              "capInsetsWidth": 1,
              "capInsetsX": 0,
              "capInsetsY": 0,
              "fileName": null,
              "fileNameData": {
                "path": "majiang_pai_pq_sj_12.png",
                "plistFile": "majiangtu/majiang_pai.plist",
                "resourceType": 1
              },
              "scale9Enable": false,
              "scale9Height": 41,
              "scale9Width": 55
            }
          },
          {
            "classname": "ImageView",
            "name": null,
            "children": [],
            "options": {
              "__type": "ImageViewSurrogate:#EditorCommon.JsonModel.Component.GUI",
              "classname": "ImageView",
              "name": "lp15",
              "ZOrder": 7,
              "actiontag": 18911313,
              "anchorPointX": 0.5,
              "anchorPointY": 0.5,
              "classType": "CocoStudio.EngineAdapterWrap.CSImageView",
              "colorB": 255,
              "colorG": 255,
              "colorR": 255,
              "customProperty": "",
              "flipX": true,
              "flipY": false,
              "height": 40,
              "ignoreSize": true,
              "layoutParameter": null,
              "opacity": 255,
              "positionPercentX": 0.04375,
              "positionPercentY": 0.06935123,
              "positionType": 0,
              "rotation": 0,
              "scaleX": 1,
              "scaleY": 1,
              "sizePercentX": 0.3375,
              "sizePercentY": 0.08948546,
              "sizeType": 0,
              "tag": 185513,
              "touchAble": false,
              "useMergedTexture": false,
              "visible": true,
              "width": 54,
              "x": 7,
              "y": 31,
              "capInsetsHeight": 1,
              "capInsetsWidth": 1,
              "capInsetsX": 0,
              "capInsetsY": 0,
              "fileName": null,
              "fileNameData": {
                "path": "majiang_pai_pq_sj_14.png",
                "plistFile": "majiangtu/majiang_pai.plist",
                "resourceType": 1
              },
              "scale9Enable": false,
              "scale9Height": 40,
              "scale9Width": 54
            }
          },
          {
            "classname": "ImageView",
            "name": null,
            "children": [],
            "options": {
              "__type": "ImageViewSurrogate:#EditorCommon.JsonModel.Component.GUI",
              "classname": "ImageView",
              "name": "lp17",
              "ZOrder": 6,
              "actiontag": 35984094,
              "anchorPointX": 0.5,
              "anchorPointY": 0.5,
              "classType": "CocoStudio.EngineAdapterWrap.CSImageView",
              "colorB": 255,
              "colorG": 255,
              "colorR": 255,
              "customProperty": "",
              "flipX": true,
              "flipY": false,
              "height": 39,
              "ignoreSize": true,
              "layoutParameter": null,
              "opacity": 255,
              "positionPercentX": 0.0125,
              "positionPercentY": 0.127516776,
              "positionType": 0,
              "rotation": 0,
              "scaleX": 1,
              "scaleY": 1,
              "sizePercentX": 0.3375,
              "sizePercentY": 0.0872483253,
              "sizeType": 0,
              "tag": 185514,
              "touchAble": false,
              "useMergedTexture": false,
              "visible": true,
              "width": 54,
              "x": 2,
              "y": 57,
              "capInsetsHeight": 1,
              "capInsetsWidth": 1,
              "capInsetsX": 0,
              "capInsetsY": 0,
              "fileName": null,
              "fileNameData": {
                "path": "majiang_pai_pq_sj_16.png",
                "plistFile": "majiangtu/majiang_pai.plist",
                "resourceType": 1
              },
              "scale9Enable": false,
              "scale9Height": 39,
              "scale9Width": 54
            }
          },
          {
            "classname": "ImageView",
            "name": null,
            "children": [],
            "options": {
              "__type": "ImageViewSurrogate:#EditorCommon.JsonModel.Component.GUI",
              "classname": "ImageView",
              "name": "lp19",
              "ZOrder": 5,
              "actiontag": 55421393,
              "anchorPointX": 0.5,
              "anchorPointY": 0.5,
              "classType": "CocoStudio.EngineAdapterWrap.CSImageView",
              "colorB": 255,
              "colorG": 255,
              "colorR": 255,
              "customProperty": "",
              "flipX": true,
              "flipY": false,
              "height": 39,
              "ignoreSize": true,
              "layoutParameter": null,
              "opacity": 255,
              "positionPercentX": -0.025,
              "positionPercentY": 0.183445185,
              "positionType": 0,
              "rotation": 0,
              "scaleX": 1,
              "scaleY": 1,
              "sizePercentX": 0.33125,
              "sizePercentY": 0.0872483253,
              "sizeType": 0,
              "tag": 185515,
              "touchAble": false,
              "useMergedTexture": false,
              "visible": true,
              "width": 53,
              "x": -4,
              "y": 82,
              "capInsetsHeight": 1,
              "capInsetsWidth": 1,
              "capInsetsX": 0,
              "capInsetsY": 0,
              "fileName": null,
              "fileNameData": {
                "path": "majiang_pai_pq_sj_18.png",
                "plistFile": "majiangtu/majiang_pai.plist",
                "resourceType": 1
              },
              "scale9Enable": false,
              "scale9Height": 39,
              "scale9Width": 53
            }
          },
          {
            "classname": "ImageView",
            "name": null,
            "children": [],
            "options": {
              "__type": "ImageViewSurrogate:#EditorCommon.JsonModel.Component.GUI",
              "classname": "ImageView",
              "name": "lp21",
              "ZOrder": 4,
              "actiontag": 29030491,
              "anchorPointX": 0.5,
              "anchorPointY": 0.5,
              "classType": "CocoStudio.EngineAdapterWrap.CSImageView",
              "colorB": 255,
              "colorG": 255,
              "colorR": 255,
              "customProperty": "",
              "flipX": true,
              "flipY": false,
              "height": 38,
              "ignoreSize": true,
              "layoutParameter": null,
              "opacity": 255,
              "positionPercentX": -0.05,
              "positionPercentY": 0.237136468,
              "positionType": 0,
              "rotation": 0,
              "scaleX": 1,
              "scaleY": 1,
              "sizePercentX": 0.325,
              "sizePercentY": 0.0850111842,
              "sizeType": 0,
              "tag": 185516,
              "touchAble": false,
              "useMergedTexture": false,
              "visible": true,
              "width": 52,
              "x": -8,
              "y": 106,
              "capInsetsHeight": 1,
              "capInsetsWidth": 1,
              "capInsetsX": 0,
              "capInsetsY": 0,
              "fileName": null,
              "fileNameData": {
                "path": "majiang_pai_pq_sj_20.png",
                "plistFile": "majiangtu/majiang_pai.plist",
                "resourceType": 1
              },
              "scale9Enable": false,
              "scale9Height": 38,
              "scale9Width": 52
            }
          },
          {
            "classname": "ImageView",
            "name": null,
            "children": [],
            "options": {
              "__type": "ImageViewSurrogate:#EditorCommon.JsonModel.Component.GUI",
              "classname": "ImageView",
              "name": "lp23",
              "ZOrder": 3,
              "actiontag": 59947829,
              "anchorPointX": 0.5,
              "anchorPointY": 0.5,
              "classType": "CocoStudio.EngineAdapterWrap.CSImageView",
              "colorB": 255,
              "colorG": 255,
              "colorR": 255,
              "customProperty": "",
              "flipX": true,
              "flipY": false,
              "height": 37,
              "ignoreSize": true,
              "layoutParameter": null,
              "opacity": 255,
              "positionPercentX": -0.08125,
              "positionPercentY": 0.290827751,
              "positionType": 0,
              "rotation": 0,
              "scaleX": 1,
              "scaleY": 1,
              "sizePercentX": 0.325,
              "sizePercentY": 0.08277405,
              "sizeType": 0,
              "tag": 185517,
              "touchAble": false,
              "useMergedTexture": false,
              "visible": true,
              "width": 52,
              "x": -13,
              "y": 130,
              "capInsetsHeight": 1,
              "capInsetsWidth": 1,
              "capInsetsX": 0,
              "capInsetsY": 0,
              "fileName": null,
              "fileNameData": {
                "path": "majiang_pai_pq_sj_22.png",
                "plistFile": "majiangtu/majiang_pai.plist",
                "resourceType": 1
              },
              "scale9Enable": false,
              "scale9Height": 37,
              "scale9Width": 52
            }
          },
          {
            "classname": "ImageView",
            "name": null,
            "children": [],
            "options": {
              "__type": "ImageViewSurrogate:#EditorCommon.JsonModel.Component.GUI",
              "classname": "ImageView",
              "name": "lp25",
              "ZOrder": 2,
              "actiontag": 2659552,
              "anchorPointX": 0.5,
              "anchorPointY": 0.5,
              "classType": "CocoStudio.EngineAdapterWrap.CSImageView",
              "colorB": 255,
              "colorG": 255,
              "colorR": 255,
              "customProperty": "",
              "flipX": true,
              "flipY": false,
              "height": 37,
              "ignoreSize": true,
              "layoutParameter": null,
              "opacity": 255,
              "positionPercentX": -0.1125,
              "positionPercentY": 0.342281878,
              "positionType": 0,
              "rotation": 0,
              "scaleX": 1,
              "scaleY": 1,
              "sizePercentX": 0.3125,
              "sizePercentY": 0.08277405,
              "sizeType": 0,
              "tag": 185518,
              "touchAble": false,
              "useMergedTexture": false,
              "visible": true,
              "width": 50,
              "x": -18,
              "y": 153,
              "capInsetsHeight": 1,
              "capInsetsWidth": 1,
              "capInsetsX": 0,
              "capInsetsY": 0,
              "fileName": null,
              "fileNameData": {
                "path": "majiang_pai_pq_sj_24.png",
                "plistFile": "majiangtu/majiang_pai.plist",
                "resourceType": 1
              },
              "scale9Enable": false,
              "scale9Height": 37,
              "scale9Width": 50
            }
          },
          {
            "classname": "ImageView",
            "name": null,
            "children": [],
            "options": {
              "__type": "ImageViewSurrogate:#EditorCommon.JsonModel.Component.GUI",
              "classname": "ImageView",
              "name": "lp27",
              "ZOrder": 1,
              "actiontag": 23935974,
              "anchorPointX": 0.5,
              "anchorPointY": 0.5,
              "classType": "CocoStudio.EngineAdapterWrap.CSImageView",
              "colorB": 255,
              "colorG": 255,
              "colorR": 255,
              "customProperty": "",
              "flipX": true,
              "flipY": false,
              "height": 37,
              "ignoreSize": true,
              "layoutParameter": null,
              "opacity": 255,
              "positionPercentX": -0.14375,
              "positionPercentY": 0.393736,
              "positionType": 0,
              "rotation": 0,
              "scaleX": 1,
              "scaleY": 1,
              "sizePercentX": 0.30625,
              "sizePercentY": 0.08277405,
              "sizeType": 0,
              "tag": 185519,
              "touchAble": false,
              "useMergedTexture": false,
              "visible": true,
              "width": 49,
              "x": -23,
              "y": 176,
              "capInsetsHeight": 1,
              "capInsetsWidth": 1,
              "capInsetsX": 0,
              "capInsetsY": 0,
              "fileName": null,
              "fileNameData": {
                "path": "majiang_pai_pq_sj_26.png",
                "plistFile": "majiangtu/majiang_pai.plist",
                "resourceType": 1
              },
              "scale9Enable": false,
              "scale9Height": 37,
              "scale9Width": 49
            }
          },
          {
            "classname": "ImageView",
            "name": null,
            "children": [],
            "options": {
              "__type": "ImageViewSurrogate:#EditorCommon.JsonModel.Component.GUI",
              "classname": "ImageView",
              "name": "lp29",
              "ZOrder": 0,
              "actiontag": 14097174,
              "anchorPointX": 0.5,
              "anchorPointY": 0.5,
              "classType": "CocoStudio.EngineAdapterWrap.CSImageView",
              "colorB": 255,
              "colorG": 255,
              "colorR": 255,
              "customProperty": "",
              "flipX": true,
              "flipY": false,
              "height": 36,
              "ignoreSize": true,
              "layoutParameter": null,
              "opacity": 255,
              "positionPercentX": -0.16875,
              "positionPercentY": 0.438478738,
              "positionType": 0,
              "rotation": 0,
              "scaleX": 1,
              "scaleY": 1,
              "sizePercentX": 0.30625,
              "sizePercentY": 0.08053691,
              "sizeType": 0,
              "tag": 185520,
              "touchAble": false,
              "useMergedTexture": false,
              "visible": true,
              "width": 49,
              "x": -27,
              "y": 196,
              "capInsetsHeight": 1,
              "capInsetsWidth": 1,
              "capInsetsX": 0,
              "capInsetsY": 0,
              "fileName": null,
              "fileNameData": {
                "path": "majiang_pai_pq_sj_28.png",
                "plistFile": "majiangtu/majiang_pai.plist",
                "resourceType": 1
              },
              "scale9Enable": false,
              "scale9Height": 36,
              "scale9Width": 49
            }
          }
        ],
        "options": {
          "__type": "ImageViewSurrogate:#EditorCommon.JsonModel.Component.GUI",
          "classname": "ImageView",
          "name": "lbg",
          "ZOrder": 0,
          "actiontag": 61272867,
          "anchorPointX": 0.5,
          "anchorPointY": 0.5,
          "classType": "CocoStudio.EngineAdapterWrap.CSImageView",
          "colorB": 255,
          "colorG": 255,
          "colorR": 255,
          "customProperty": "",
          "flipX": false,
          "flipY": false,
          "height": 447,
          "ignoreSize": false,
          "layoutParameter": null,
          "opacity": 255,
          "positionPercentX": 0.749218762,
          "positionPercentY": 0.5638889,
          "positionType": 0,
          "rotation": 0,
          "scaleX": 1,
          "scaleY": 1,
          "sizePercentX": 0.125,
          "sizePercentY": 0.620833337,
          "sizeType": 0,
          "tag": 185490,
          "touchAble": false,
          "useMergedTexture": false,
          "visible": true,
          "width": 160,
          "x": 959,
          "y": 406,
          "capInsetsHeight": 1,
          "capInsetsWidth": 1,
          "capInsetsX": 0,
          "capInsetsY": 0,
          "fileName": null,
          "fileNameData": {
            "path": "touming.png",
            "plistFile": "",
            "resourceType": 0
          },
          "scale9Enable": false,
          "scale9Height": 447,
          "scale9Width": 160
        }
      }
    ],
    "options": {
      "__type": "PanelSurrogate:#EditorCommon.JsonModel.Component.GUI",
      "classname": "Panel",
      "name": "Panel_234",
      "ZOrder": 0,
      "actiontag": -1,
      "anchorPointX": 0,
      "anchorPointY": 0,
      "classType": "CocoStudio.EngineAdapterWrap.CSPanel",
      "colorB": 255,
      "colorG": 255,
      "colorR": 255,
      "customProperty": "",
      "flipX": false,
      "flipY": false,
      "height": 720,
      "ignoreSize": false,
      "layoutParameter": null,
      "opacity": 255,
      "positionPercentX": 0,
      "positionPercentY": 0,
      "positionType": 0,
      "rotation": 0,
      "scaleX": 1,
      "scaleY": 1,
      "sizePercentX": 1,
      "sizePercentY": 1,
      "sizeType": 0,
      "tag": 185262,
      "touchAble": true,
      "useMergedTexture": false,
      "visible": true,
      "width": 1280,
      "x": 0,
      "y": 0,
      "adaptScreen": false,
      "backGroundImage": null,
      "backGroundImageData": null,
      "backGroundScale9Enable": false,
      "bgColorB": 255,
      "bgColorG": 200,
      "bgColorOpacity": 0,
      "bgColorR": 150,
      "bgEndColorB": 255,
      "bgEndColorG": 200,
      "bgEndColorR": 150,
      "bgStartColorB": 255,
      "bgStartColorG": 255,
      "bgStartColorR": 255,
      "capInsetsHeight": 1,
      "capInsetsWidth": 1,
      "capInsetsX": 0,
      "capInsetsY": 0,
      "clipAble": false,
      "colorType": 1,
      "layoutType": 0,
      "vectorX": 0,
      "vectorY": -0.5
    }
  }
}